video_bookmarks/__init__.py
video_bookmarks/main.py
video_bookmarks-1.0.0.dist-info/METADATA
video_bookmarks-1.0.0.dist-info/WHEEL
video_bookmarks-1.0.0.dist-info/entry_points.txt
video_bookmarks-1.0.0.dist-info/top_level.txt
video_bookmarks-1.0.0.dist-info/RECORD
