Metadata-Version: 2.4
Name: video-bookmarks
Version: 1.0.0
Summary: A command-line wrapper of the mpv video player to create video bookmarks
Author-email: "@readwithai" <talwrii@gmail.com>
Maintainer-email: Claude <talwrii@gmail.com>
License: MIT
Project-URL: Homepage, https://github.com/talwrii/video-bookmarks
Project-URL: Bug Tracker, https://github.com/talwrii/video-bookmarks/issues
Keywords: video,bookmarks,mpv,cli,video-editing,timestamps
Classifier: Development Status :: 4 - Beta
Classifier: Environment :: Console
Classifier: Intended Audience :: Developers
Classifier: Intended Audience :: End Users/Desktop
Classifier: License :: OSI Approved :: MIT License
Classifier: Operating System :: POSIX :: Linux
Classifier: Operating System :: MacOS
Classifier: Programming Language :: Python :: 3
Classifier: Programming Language :: Python :: 3.8
Classifier: Programming Language :: Python :: 3.9
Classifier: Programming Language :: Python :: 3.10
Classifier: Programming Language :: Python :: 3.11
Classifier: Programming Language :: Python :: 3.12
Classifier: Topic :: Multimedia :: Video
Classifier: Topic :: Utilities
Requires-Python: >=3.8
Provides-Extra: dev
Requires-Dist: pytest>=7.0.0; extra == "dev"
Requires-Dist: pytest-cov>=4.0.0; extra == "dev"
Requires-Dist: black>=23.0.0; extra == "dev"
Requires-Dist: flake8>=6.0.0; extra == "dev"
Requires-Dist: mypy>=1.0.0; extra == "dev"
